README
setup.py
django_ip_authn/__init__.py
django_ip_authn/authentication.py
django_ip_authn.egg-info/PKG-INFO
django_ip_authn.egg-info/SOURCES.txt
django_ip_authn.egg-info/dependency_links.txt
django_ip_authn.egg-info/top_level.txt