Metadata-Version: 1.1
Name: django-ip-authn
Version: 0.2.1
Summary: IP number based authentication for Django
Home-page: https://github.com/Felspar/django-ip-authn
Author: Kirit Saelensminde
Author-email: kirit@felspar.com
License: Boost Software License - Version 1.0 - August 17th, 2003
Keywords: django authn authentication ip
Platform: UNKNOWN
Classifier: Development Status :: 3 - Alpha
Classifier: Framework :: Django
Classifier: Intended Audience :: Developers
Classifier: Programming Language :: Python
Classifier: Topic :: Software Development :: Libraries :: Python Modules
Classifier: License :: OSI Approved
